CHANGES.rst
CONTRIBUTORS.rst
MANIFEST.in
README.rst
setup.cfg
setup.py
docs/LICENSE.GPL
docs/LICENSE.rst
docs/source/conf.py
docs/source/index.rst
docs/source/_static/logo.png
docs/source/_templates/.gitkeep
src/plone/__init__.py
src/plone.formwidget.relateditems.egg-info/PKG-INFO
src/plone.formwidget.relateditems.egg-info/SOURCES.txt
src/plone.formwidget.relateditems.egg-info/dependency_links.txt
src/plone.formwidget.relateditems.egg-info/entry_points.txt
src/plone.formwidget.relateditems.egg-info/namespace_packages.txt
src/plone.formwidget.relateditems.egg-info/not-zip-safe
src/plone.formwidget.relateditems.egg-info/requires.txt
src/plone.formwidget.relateditems.egg-info/top_level.txt
src/plone/formwidget/__init__.py
src/plone/formwidget/relateditems/__init__.py
src/plone/formwidget/relateditems/config.py
src/plone/formwidget/relateditems/configure.zcml
src/plone/formwidget/relateditems/interfaces.py
src/plone/formwidget/relateditems/profiles.zcml
src/plone/formwidget/relateditems/setuphandlers.py
src/plone/formwidget/relateditems/testing.py
src/plone/formwidget/relateditems/widget.py
src/plone/formwidget/relateditems/widget_display.pt
src/plone/formwidget/relateditems/profiles/default/browserlayer.xml
src/plone/formwidget/relateditems/profiles/default/metadata.xml
src/plone/formwidget/relateditems/profiles/default/registry.xml
src/plone/formwidget/relateditems/profiles/uninstall/browserlayer.xml
src/plone/formwidget/relateditems/static/relateditems.css
src/plone/formwidget/relateditems/tests/__init__.py
src/plone/formwidget/relateditems/tests/test_setup.py
src/plone/formwidget/relateditems/tests/test_widget.py