Metadata-Version: 1.1
Name: plone.formwidget.relateditems
Version: 0.2
Summary: An advanced related items widget for Plone.
Home-page: https://github.com/it-spirit/plone.formwidget.relateditems
Author: it-spirit
Author-email: development@it-spir.it
License: GPL version 2
Download-URL: https://pypi.python.org/pypi/plone.formwidget.relateditems
Keywords: Python Plone Widget
Platform: UNKNOWN
Classifier: Development Status :: 4 - Beta
Classifier: Environment :: Web Environment
Classifier: Framework :: Plone
Classifier: Framework :: Plone :: 5.0
Classifier: Framework :: Plone :: 5.1
Classifier: Intended Audience :: Developers
Classifier: License :: OSI Approved :: GNU General Public License v2 (GPLv2)
Classifier: Programming Language :: Python
Classifier: Programming Language :: Python :: 2.7
